whominator/__init__.py
whominator/whominate.py
whominator/whominator.py
whominator-0.1.1.dist-info/LICENSE
whominator-0.1.1.dist-info/METADATA
whominator-0.1.1.dist-info/WHEEL
whominator-0.1.1.dist-info/entry_points.txt
whominator-0.1.1.dist-info/top_level.txt
whominator-0.1.1.dist-info/RECORD
