Metadata-Version: 2.1
Name: whominator
Version: 0.1.1
Summary: corrects who to whom
Home-page: https://github.com/96jonesa/whominator
Author: 96jonesa
Author-email: ajones96@uw.edu
License: GNU General Public License v3 (GPLv3)
Platform: UNKNOWN
Classifier: License :: OSI Approved :: GNU General Public License v3 (GPLv3)
Classifier: Operating System :: OS Independent
Classifier: Programming Language :: Python :: 3.6
Requires-Python: >=3.6
Requires-Dist: spacy
Requires-Dist: flair
